source/fa.v
// -----------------------------------------------------------------------------
//  Title         : 1bit full-adder with output latch
//  Project       : 
// -----------------------------------------------------------------------------
//  File          : fa.v
//  Author        : 
//  Created       : 2018/ 3/xx
//  Last modified : 
// -----------------------------------------------------------------------------
//  Description   : 1bit full-adder with output latch
// -----------------------------------------------------------------------------
//  Copyright (C) 2018 ??? All Rights Reserved.
// -----------------------------------------------------------------------------

`timescale  1ns/1ps

module fa(
    input   wire    ck,
    input   wire    rst,
    input   wire    a,
    input   wire    b,
    input   wire    ci,
    output  wire    s,
    output  wire    co
);

    reg       r_s, r_co;

    assign s = r_s, co = r_co;

    always @(posedge ck) begin
        if (rst == 1'b1) begin
            r_s <= 1'b0; r_co <= 1'b0;
        end
        else begin
            {r_co, r_s} = {a + b + ci};
//            r_s <= a ^ b ^ ci;
//            r_co <= (a & b) | (b & ci) | (ci & a);
        end
    end
endmodule

source/fa_tb.v
// -----------------------------------------------------------------------------
//  Title         : 1bit full-adder with output latch (test bench)
//  Project       : 
// -----------------------------------------------------------------------------
//  File          : fa_tb.v
//  Author        : 
//  Created       : 2018/ 3/xx
//  Last modified : 
// -----------------------------------------------------------------------------
//  Description   : 1bit full-adder with output latch
// -----------------------------------------------------------------------------
//  Copyright (C) 2018 ??? All Rights Reserved.
// -----------------------------------------------------------------------------

`timescale  1ns/1ps

module fa_tb();
    reg             ck, rst;
    reg     [2:0]   i;
    wire            s, co, a, b, ci;

    assign {a, b, ci} = i;
   
    always begin
        #50; ck = ~ck;
    end

    initial begin
        $dumpfile("fa_tb.vcd");
        $dumpvars(0,fa_tb);

        ck <= 0; rst <= 1; i <= 3'b000;
        #100; rst <= 0;
        #100; i <= 3'b001;
        #100; i <= 3'b010;
        #100; i <= 3'b011;
        #100; i <= 3'b100;
        #100; i <= 3'b101;
        #100; i <= 3'b110;
        #100; i <= 3'b111;
        #20000 $finish;
    end

    fa fa(.ck(ck), .rst(rst), .a(a), .b(b), .ci(ci), .s(s), .co(co));

endmodule

source/fa_tb.vcd
$date
	Sat Mar 17 19:44:56 2018
$end
$version
	Icarus Verilog
$end
$timescale
	1ps
$end
$scope module fa_tb $end
$var wire 1 ! s $end
$var wire 1 " co $end
$var wire 1 # ci $end
$var wire 1 $ b $end
$var wire 1 % a $end
$var reg 1 & ck $end
$var reg 3 ' i [2:0] $end
$var reg 1 ( rst $end
$scope module fa $end
$var wire 1 % a $end
$var wire 1 $ b $end
$var wire 1 # ci $end
$var wire 1 & ck $end
$var wire 1 " co $end
$var wire 1 ( rst $end
$var wire 1 ! s $end
$var reg 1 ) r_co $end
$var reg 1 * r_s $end
$upscope $end
$upscope $end
$enddefinitions $end
#0
$dumpvars
x*
x)
1(
b0 '
0&
0%
0$
0#
x"
x!
$end
#50000
0"
0)
0!
0*
1&
#100000
0(
0&
#150000
1&
#200000
1#
b1 '
0&
#250000
1!
1*
1&
#300000
1$
0#
b10 '
0&
#350000
1&
#400000
1#
b11 '
0&
#450000
0!
0*
1&
#500000
1%
0$
0#
b100 '
0&
#550000
1!
1*
1&
#600000
1#
b101 '
0&
#650000
0!
0*
1&
#700000
1$
0#
b110 '
0&
#750000
1&
#800000
1#
b111 '
0&
#850000
1!
1*
1&
