source/fa_tb.v
module fa_tb();
   reg ck, rst;
   reg [2:0] i;
   wire s, co, a, b, ci;

   assign{a, b, ci} = i;
   
   always begin
      #50; ck = ~ck;
   end

   initial begin
     $dumpfile("fa_tb.vcd");
     $dumpvars(0,fa_tb);

      ck <= 0; rst <= 1; i <= 3'b000;
      #100; rst <= 0;
      #100; i <= 3'b001;
      #100; i <= 3'b010;
      #100; i <= 3'b011;
      #100; i <= 3'b100;
      #100; i <= 3'b101;
      #100; i <= 3'b110;
      #100; i <= 3'b111;
      #20000 $finish;
   end
endmodule

source/fa_tb.vcd
$date
	Thu Mar 15 14:04:23 2018
$end
$version
	Icarus Verilog
$end
$timescale
	1s
$end
$scope module fa_tb $end
$var wire 1 ! ci $end
$var wire 1 " b $end
$var wire 1 # a $end
$var reg 1 $ ck $end
$var reg 3 % i [2:0] $end
$var reg 1 & rst $end
$upscope $end
$enddefinitions $end
#0
$dumpvars
1&
b0 %
0$
0#
0"
0!
$end
#50
1$
#100
0&
0$
#150
1$
#200
1!
b1 %
0$
#250
1$
#300
1"
0!
b10 %
0$
#350
1$
#400
1!
b11 %
0$
#450
1$
#500
1#
0"
0!
b100 %
0$
#550
1$
#600
1!
b101 %
0$
#650
1$
#700
1"
0!
b110 %
0$
#750
1$
#800
1!
b111 %
0$
